{"company_codes_occur": "", "art": "", "company_codes_association": "", "language_code": "en", "person_codes": "", "word_count": 99, "an": "PAPRIN0020191008efa70000e", "region_of_origin": "ASIA PAKIS SASIAZ ", "company_codes": "", "publication_date": 1570406400000, "market_index_codes": "", "source_name": "Pakistan Press International", "company_codes_relevance_ticker_exchange": "", "publisher_name": "Pakistan Press International Information Services", "ingestion_datetime": 1570541845000, "document_type": "article", "byline": "", "copyright": "Copyright \u00a9 2019. Pakistan Press International ", "title": "Minister: (Kashmir issue will come under discussion during PM's China visit: Rashid)", "section": "", "company_codes_occur_ticker_exchange": "", "snippet": "Minister for Railways Sheikh Rashid Ahmad has said that economy and Kashmir issue will come under discussion during Prime Minister Imran Khan visit to China.\n\nIn his special message before leaving for China last night, he said Pak-China friendship is higher than Himalayas and China is all seasoned friend of Pakistan.", "company_codes_relevance": "", "body": "He urged the opposition not to put Pakistan in crises to gain their political interests. He said Imran Khan will play a historic role in freedom of Kashmir and pulling country out of crisis.", "subject_codes": ",gdip,gpol,gvexe,gcat,gpir,gvbod,", "company_codes_association_ticker_exchange": "", "company_codes_lineage": "", "source_code": "PAPRIN", "industry_codes": "", "modification_datetime": 1570541845000, "currency_codes": "", "modification_date": 1585477836657, "region_codes": ",pakis,kash,china,apacz,asiaz,bric,chinaz,devgcoz,dvpcoz,easiaz,indsubz,sasiaz,", "company_codes_lineage_ticker_exchange": "", "company_codes_ticker_exchange": "", "credit": "", "publication_datetime": 1570406400000, "company_codes_about_ticker_exchange": "", "company_codes_about": "", "action": "add", "dateline": null}