{"company_codes_occur": ",mufc,", "art": "", "company_codes_association": "", "language_code": "en", "person_codes": "", "word_count": 1003, "an": "APRS000020191002efa200jod", "region_of_origin": "NAMZ USA ", "company_codes": ",mufc,mufc,sahrc,", "publication_date": 1570023158923, "market_index_codes": "", "source_name": "Associated Press Newswires", "company_codes_relevance_ticker_exchange": "", "publisher_name": "The Associated Press", "ingestion_datetime": 1570023186000, "document_type": "article", "byline": "", "copyright": "(c) 2019.  The Associated Press.  All Rights Reserved. ", "title": "BC-AP--AP Sports Digest, AP", "section": "", "company_codes_occur_ticker_exchange": "", "snippet": "WORLD SPORTS at 1330 GMT\n\nTOP STORIES:", "company_codes_relevance": ",sahrc,mufc,", "body": "SOC--CHAMPIONS LEAGUE ROUNDUP\n\nDefending champion Liverpool plays Austrian team Salzburg at Anfield, and Barcelona hosts Inter Milan, in Champions League group games on Wednesday. UPCOMING: 600 words by 2230 GMT, photos. With separates on eight games.\n\nRGU--RWC-NEW ZEALAND-CANADA\n\nOITA, Japan _ Refreshed after an 11-day break, New Zealand gave Canada a 63-0 thrashing that was expected in the Rugby World Cup on Wednesday. By Foster Niumata. SENT: 750 words, photos.\n\nATH--WORLDS-SALAZAR INVESTIGATION\n\nDOHA, Qatar _ Suspicious athletes triggered coaching great Alberto Salazar's downfall. By Eddie Pells. SENT: 1,370 words, photos.\n\nATH--WORLDS-LYLES\n\nDOHA, Qatar _ Gold medal secured, Noah Lyles took a lap around the sparsely filled stadium with a big decision weighing on him _ vanilla or Oreo milkshake? By Pat Graham. SENT: 590 words, photos.\n\nCRI--INDIA-SOUTH AFRICA\n\nVISAKHAPATNAM, India _ Rohit Sharma scored a century in his test debut as an opener as India reached 202-0 at stumps with rain preventing any play in the final session on Day 1 of the first test against South Africa on Wednesday. By Chetan Narula. SENT: 325 words, photos.\n\nOLY--TOKYO-LABOR COMPLAINT\n\nTOKYO _ An international labor union investigating worker safety and the use of migrant workers at venues for next year's Tokyo Olympics is asking for a joint inspection of construction sites and an open interview with workers. By Stephen Wade. SENT: 620 words, photos.\n\nSOC--MAN CITY-SILVA CHARGED\n\nManchester City midfielder Bernardo Silva was charged with misconduct by the English Football Association on Wednesday for posting a tweet which compared teammate Benjamin Mendy to the character on a packet of Conguitos chocolates. By Steve Douglas. SENT: 320 words, photos.\n\nSOC--MAN UNITED-POGBA\n\nMANCHESTER, England _ Manchester United says Paul Pogba has been managing a foot injury for more than a month and requires \"a period of further rest and conservative treatment.\" SENT: 160 words.\n\nSOC--FIFA-SALA CLAIM\n\nCardiff says it will appeal to sport\u2019s highest court against FIFA\u2019s ruling that the club should pay 6 million euros ($6.5 million) to Nantes as a first installment of the transfer fee for the late Argentine striker Emiliano Sala. SENT: 300 words, photo.\n\nSOC--BARCELONA-INTER\n\nBARCELONA, Spain _ Lionel Messi is doubtful for Barcelona\u2019s Champions League Group F match against Inter Milan. By Joseph Wilson. UPCOMING: 130 words by 2100 GMT, 500 words by 2200 GMT, photos.\n\nSOC--LIVERPOOL-SALZBURG\n\nLIVERPOOL, England _ After starting its Champions League title defense with a loss at Napoli, Liverpool looks to get its group-stage campaign back on track by beating Austrian team Salzburg. UPCOMING: 400 words by 2100 GMT, photos.\n\nSOC--LILLE-CHELSEA\n\nLILLE, France _ Lille and Chelsea look for their first points in the Champions League group stage when they meet in France. They both lost their opening group games. UPCOMING: 300 words by 2200 GMT, photos.\n\nSOC--VALENCIA-AJAX\n\nVALENCIA, Spain _ Valencia goes for its second win in a row when it hosts Ajax in Group H of the Champions League. UPCOMING: 300 words by 2100 GMT, photos.\n\nSOC--ZENIT-BENFICA\n\nST. PETERSBURG, Russia _ Looking for their first win in the Champions League this season, Zenit St. Petersburg and Benfica meet in Russia in Group G. UPCOMING: 250 words by 2100 GMT, photos.\n\nTEN--JAPAN OPEN\n\nTOKYO _Novak Djokovic reached the quarterfinals of the Japan Open on Wednesday by beating Japanese wild-card entry Go Soeda 6-3, 7-5. By Jim Armstrong. SENT: 495 words, photos.\n\nTEN--CHINA OPEN\n\nBEIJING _ Andy Murray won consecutive singles matches for the first time since undergoing hip surgery in January while U.S. Open champion Bianca Andreescu won her 15th in a row at the China Open on Wednesday. SENT: 170 words, will be updated.\n\nRGU--RWC-FRANCE-UNITED STATES\n\nFUKUOKA, Japan _ Just when France appeared vulnerable against a spirited U.S. lineup, its bench came to the rescue to seal a 33-9 win which kept Les Bleus firmly on track for the knockout stages at the Rugby World Cup. By Jerome Pugmire. SENT: 845 words, photos.\n\nRGU--RWC-AUSTRALIA TEAM\n\nOITA, Japan _ Teenager Jordan Petaia will make his test debut at the Rugby World Cup after being selected among 13 changes to Australia's starting lineup for Saturday's Pool D game against Uruguay. SENT: 570 words, photos.\n\nRGU--RWC-SOUTH AFRICA-ITALY PREVIEW\n\nHAMAMATSU, Japan _ It's a pool-stage game with a knockout effect at the Rugby World Cup. Both teams are relying on their heavyweights to settle it. Realistically, South Africa and Italy both need to win to stay in contention at the World Cup when they play in Pool B on Friday. By Gerald Imray. SENT: 780 words, photos.\n\nRGU--RWC-ETZEBETH-COURT CASE\n\nHAMAMATSU, Japan _ Springboks lock Eben Etzebeth could be forced to leave Japan midway through the Rugby World Cup after the South African Human Rights Commission said it was taking him to court over a case of alleged physical and racial abuse. By Gerald Imray. SENT: 525 words, photos.\n\nRGU--RWC-IRELAND DEFENSE\n\nKOBE, Japan _ Three of the four offside calls against Ireland were apparently wrong. That hasn't stopped Ireland from making sure the chances of being whistled offside again in the Rugby World Cup are slim. SENT: 490 words, photos.\n\nCRI--PAKISTAN-SRI LANKA\n\nKARACHI, Pakistan _ Sri Lanka won the toss and chose to bat in the third and final one-day international against Pakistan on Wednesday. SENT: 280 words, photos. Will be updated.\n\nCRI--AUSTRALIA-HEALY-WORLD RECORD\n\nSYDNEY _ Australian Alyssa Healy set a world record for the largest run total in a women's Twenty20 cricket international with an unbeaten 148 off 61 balls against Sri Lanka on Wednesday. SENT: 170 words.\n\nYOUR QUERIES: Questions and story requests are welcome. Contact your local AP bureau or the AP International Sports Desk in London by telephone at +44 207 427 4224 or email lonsports@ap.org.", "subject_codes": ",gspo,gsocc,gcric,grugu,nadv,nsum,ncat,nfact,nfce,niwe,nrgn,", "company_codes_association_ticker_exchange": "", "company_codes_lineage": "", "source_code": "APRS", "industry_codes": "", "modification_datetime": 1570023186000, "currency_codes": "", "modification_date": 1585464302689, "region_codes": ",jap,easiaz,spain,fra,eland,arg,doha,italy,lille,pakis,porl,qatar,srilan,usa,tokyo,apacz,asiaz,devgcoz,dvpcoz,eecz,eurz,gulfstz,indsubz,kanag,lamz,meastz,medz,namz,nordpa,samz,sasiaz,uk,wasiaz,weurz,", "company_codes_lineage_ticker_exchange": "", "company_codes_ticker_exchange": "", "credit": "", "publication_datetime": 1570023158923, "company_codes_about_ticker_exchange": "", "company_codes_about": "", "action": "add", "dateline": null}