{"company_codes_occur": "", "art": "", "company_codes_association": "", "language_code": "en", "person_codes": ",168205546,168205546,168205546,171527558,171527558,171527558,", "word_count": 247, "an": "ASPTOD0020191012efab0000m", "region_of_origin": "ASIA PAKIS SASIAZ ", "company_codes": "", "publication_date": 1570752000000, "market_index_codes": "", "source_name": "Pakistan Today", "company_codes_relevance_ticker_exchange": "", "publisher_name": "Nawa Media (Pvt.) Limited", "ingestion_datetime": 1570890618000, "document_type": "article", "byline": "", "copyright": "Copyright \u00a9 2019. Nawa Media (PVT.) Limited. ", "title": "Chinese investors keen to invest in Punjab housing sector", "section": "", "company_codes_occur_ticker_exchange": "", "snippet": "A delegation of Meishang International Group Investment Holding Limited of China led by its Chairman Prof. Guo Rongzong called on the Punjab Chief Minister Sardar Usman Buzdar here at CM Office on Friday and showed a keen interest in investment in the housing sector of Punjab.\n\nProf. Guo Rongzong showed interest in investing in the construction of low-cost houses for low-income families adding that they want to construct two lakh such houses in Punjab.", "company_codes_relevance": "", "body": "Talking on the occasion, the chief minister welcomed Chinese investors' interest and assured to provide every possible facility. He added that vast opportunities for investment are available and added that foreign investment will be fully protected in the province.\n\nHe directed the line departments to submit comprehensive recommendations after analyzing the proposal and future roadmap should be prepared at the earliest. He said that the PTI government has launched the Naya Pakistan Housing programme and work is being done speedily.\n\nUsman Buzdar informed that construction of high-rise buildings has been allowed by the Punjab government and hoped that this would boost economic activities.\n\nDirector and Overseas Project President Michael Tu, Overseas Project Manager Sean Crawford and Secretary Samuel Li were included in the delegation. Provincial Housing Minister Mian Mahmood ur Rasheed, Chairman PBIT Sardar Tanvir Ilyas, Chief Secretary, secretaries of housing, P and D and industries departments, CEO PBIT, Secretary Taskforce Atif Mayo and others were also present on the occasion.", "subject_codes": "", "company_codes_association_ticker_exchange": "", "company_codes_lineage": "", "source_code": "ASPTOD", "industry_codes": ",i5010022,i501,iconst,icre,", "modification_datetime": 1570890618000, "currency_codes": "", "modification_date": 1585465929022, "region_codes": ",punjab,china,india,laho,pakis,apacz,asiaz,bric,chinaz,devgcoz,dvpcoz,easiaz,indsubz,sasiaz,", "company_codes_lineage_ticker_exchange": "", "company_codes_ticker_exchange": "", "credit": "", "publication_datetime": 1570752000000, "company_codes_about_ticker_exchange": "", "company_codes_about": "", "action": "add", "dateline": null}