{"company_codes_occur": "", "art": "", "company_codes_association": "", "language_code": "en", "person_codes": ",157338460,157338460,", "word_count": 182, "an": "NBBALU0020191018efai0001x", "region_of_origin": "ASIA PAKIS SASIAZ ", "company_codes": "", "publication_date": 1571356800000, "market_index_codes": "", "source_name": "The Balochistan Times", "company_codes_relevance_ticker_exchange": "", "publisher_name": "Asianet-Pakistan", "ingestion_datetime": 1571408585000, "document_type": "article", "byline": "", "copyright": "\u00a9 2019 The Balochistan Times ", "title": "Chinese Ambassador calls on IPC minister", "section": "", "company_codes_occur_ticker_exchange": "", "snippet": "Chinese Ambassador, Yao Jing along with his team called on Federal Minister for Inter Provincial Coordination (IPC) Dr Fehmida Mirza in her office on Thursday and held deliberations for inauguration of Sino-Pak Sister Cities Forum.\n\nThe forum aimed at cultivating practical cooperation and promoting development projects under the Sister Cities Project between China and Pakistan is likely to be held next month, said a press release issued here.", "company_codes_relevance": "", "body": "'Our government seeks to cultivate tangible outcomes from Sister Cities Project with China. It will enhance bilateral relations and transfer benefits of friendship with China to the grass-root level,' the minister said.\n\nShe said the forum should facilitate cooperation in province-city management, service delivery mechanism, public health, model village, environmental protection, poverty alleviation, trade and investment, tourism cooperation, urbanisation and vocational/professional education.\n\nChinese Ambassador acknowledged the proposal prepared by the IPC Ministry for the establishment of Sino-Pak Forum for Sister Cities Project. He said project would enhance mutual understanding between local governments of the two countries and boost socioeconomic ties of both countries.", "subject_codes": ",gdip,gpol,gcat,gpir,", "company_codes_association_ticker_exchange": "", "company_codes_lineage": "", "source_code": "NBBALU", "industry_codes": "", "modification_datetime": 1571408585000, "currency_codes": "", "modification_date": 1585486641189, "region_codes": ",china,easiaz,chinaz,pakis,apacz,asiaz,bric,devgcoz,dvpcoz,indsubz,sasiaz,", "company_codes_lineage_ticker_exchange": "", "company_codes_ticker_exchange": "", "credit": "", "publication_datetime": 1571356800000, "company_codes_about_ticker_exchange": "", "company_codes_about": "", "action": "add", "dateline": null}