{"company_codes_occur": ",prvmgu,", "art": "", "company_codes_association": "", "language_code": "en", "person_codes": ",15733362,15733362,", "word_count": 650, "an": "NBBALU0020190307ef370000x", "region_of_origin": "ASIA PAKIS SASIAZ ", "company_codes": ",prvmgu,prvmgu,", "publication_date": 1551916800000, "market_index_codes": "", "source_name": "The Balochistan Times", "company_codes_relevance_ticker_exchange": "", "publisher_name": "Asianet-Pakistan", "ingestion_datetime": 1551946041000, "document_type": "article", "byline": "", "copyright": "\u00a9 2019 The Balochistan Times ", "title": "National Men and Women Throw Ball Championship from March 19: Arshad Hussain", "section": "", "company_codes_occur_ticker_exchange": "", "snippet": "National Men and Women Throw Ball Championship will be organized with the collaboration of District Govt and Directorate of Sports Khyber Pakhtunkhwa here at indoor hall of the Sahibzada Abdul Qayyum Auditorium University of Peshawar Campus from March 19, 2019.\n\nThis was stated by Secretary KP Throw Ball Association Arshad Hussain while addressing a press conference here at local hotel on Wednesday. Regional Sports Officer Jamshed Baloch, Member Sports and Culture Committee District Govt Waseem Akram were also present.", "company_codes_relevance": ",prvmgu,", "body": "Arshad Hussain lauded Nazim Peshawar Mohammad Asim Khan and Director General Sports KP Junaid Khan for extending all out financial support in holding for the first time Throw Ball Men and Women Championships in Peshawar. He said Throw Ball is newly introduced Games of Malaysia in Pakistan and it would for the first time that Peshawar is hosting both male and female Championships.\n\nHe said along with the National Championship, a fresher course will also be organized in order to provide much updates rules and regulations to the referees and coaches associated with this Game in Pakistan.\n\nArshad Hussain disclosed that referees and coaches course will be part of the Championships and Pakistan Throw Ball Federation has already directed all the referees and coaches to attend. He said a total of 15 teams comprising Punjab, Sindh, Balochistan, Islamabad, Gilgit-Baltistan, team of merger tribal districts, Police, Rangers, City School Bajria, City School Lahore and City School Karachi, Agha Khan Youth Board, and Khyber Pakhtunkhwa will be taking part in the Championship.\n\nHe said all arrangements in this connection have been given final touches as the teams, officials, referees and coaches would be provided accommodations.\n\nArshad Hussain said that Nazim Peshawar Mohammad Asim Khan will grace the occasion as chief guest at the opening ceremony. Vice Chancellor University of Peshawar Professor Dr. Mohammad Asif Khan, Director General Sports University of Peshawar Bahre Karam will also be invited for the opening ceremony.\n\nChina Power Hub Generation Company, Saindak Project donated for flood victims\n\nQUETTA: Deputy Commissioner Lasbela Shabir Ahmed Mangal on Wednesday said measures were being continued to ensure provision of better facilities including rehabilitation and compensation of flood victims in the district.\n\nHe expressed this while talking to CSR Manager of China Power Hub Generation Company (CPHGC), Atif and Saindak Project's MCC Resources Development Limited (MRDL)'s Deputy Director Masood Hussain when both officials, on behalf of their departments, handed over laden trucks of donations of goods to DC Shabir Ahmed Mengal for flood victims.\n\nThe DC said that ongoing relief operations were being scrutinized in various established camps of flood victims in supervision of Assistant Commissioner Bela Jameel Ahmed Baloch and officials of Provincial Disaster Management Authority (PDMA).\n\n'Surveys are being continued under formed teams in different flood hit areas including Adora, Orgai, Lahkara, Retalara, Gadri and others in order to rehabilitate affected areas according to reports of surveys for better way', he said,\n\nShabir Ahmed said the directives had been issued to officials of agriculture and livestock departments to conduct surveys to estimate regarding losses of agriculture and livestock's in flood stricken areas, so that compensations would provide cultivators in positive way.\n\nHe appreciated the teams including Pakistan Army, administration, PDMA, rescue and other non-governmental organizations who were busy in better help of the victims through maintaining cooperation with them in camps.\n\nThe DC lauded efforts of China Power Hub Generation Project's official Major Atif and Deputy Director of Sandak Project Masood Hussain for donation goods for the victims. The PDMA would distribute these goods among flood victims, he said.\n\nBoth officials also praised the DC, rescue teams including Pakistan Army and said they had saved precious lives of people after hectic efforts who had submerged in flood water, adding such donation processes would be continued for supporting of needy people from their departments.", "subject_codes": ",gspo,ncat,nfact,nfce,nrgn,", "company_codes_association_ticker_exchange": "", "company_codes_lineage": "", "source_code": "NBBALU", "industry_codes": "", "modification_datetime": 1551946041000, "currency_codes": "", "modification_date": 1585467767677, "region_codes": ",pakis,asiaz,devgcoz,dvpcoz,indsubz,sasiaz,", "company_codes_lineage_ticker_exchange": "", "company_codes_ticker_exchange": "", "credit": "", "publication_datetime": 1551916800000, "company_codes_about_ticker_exchange": "", "company_codes_about": "", "action": "add", "dateline": null}