{"company_codes_occur": ",oblrve,", "art": "", "company_codes_association": "", "language_code": "en", "person_codes": ",110608473,110608473,115703850,115703850,", "word_count": 198, "an": "ASETRI0020190425ef4o00007", "region_of_origin": "ASIA PAKIS SASIAZ ", "company_codes": ",oblrve,oblrve,", "publication_date": 1556064000000, "market_index_codes": "", "source_name": "The Express Tribune", "company_codes_relevance_ticker_exchange": "", "publisher_name": "The Express Tribune", "ingestion_datetime": 1556177238000, "document_type": "article", "byline": "", "copyright": "Copyright \u00a9 2019. The Express Tribune News Network. ", "title": "BRI forum: PM Imran to leave for China tomorrow", "section": "", "company_codes_occur_ticker_exchange": "", "snippet": "Prime Minister Imran Khan will leave for China on Thursday to attend the second Belt and Road forum for International Cooperation scheduled to be held from April 25-27 in Beijing.\n\nA high-level delegation comprising federal ministers and other senior officials will accompany the premier during his visit.", "company_codes_relevance": ",oblrve,", "body": "On the first day, he will attend the inaugural session of the forum and deliver a keynote speech besides attending the state banquet to be hosted by Chinese President Xi Jinping in the honour of world leaders.\n\nHe, along with other leaders, will attend the leaders' roundtable sessions on the event's second day.\n\nThe prime minister will also hold meetings with President Xi and his Chinese counterpart Li Keqiang to promote bilateral relations between the two countries.\n\nHe will also meet world leaders on the sidelines of the forum.\n\nOn Tuesday, China had welcomed PM Imran's participation in the forum.\n\nChinese Foreign Ministry Spokesperson Geng Shuang, during a routine press briefing said that the China-Pakistan Economic Corridor, a flagship project of Belt and Road Initiative had delivered benefits to the people of two countries with concrete outcomes.", "subject_codes": ",gvexe,gdip,gpol,gcat,gpir,gvbod,", "company_codes_association_ticker_exchange": "", "company_codes_lineage": "", "source_code": "ASETRI", "industry_codes": "", "modification_datetime": 1556177238000, "currency_codes": "", "modification_date": 1585475603715, "region_codes": ",china,easiaz,chinaz,pakis,apacz,asiaz,bric,devgcoz,dvpcoz,indsubz,sasiaz,", "company_codes_lineage_ticker_exchange": "", "company_codes_ticker_exchange": "", "credit": "", "publication_datetime": 1556064000000, "company_codes_about_ticker_exchange": "", "company_codes_about": "", "action": "add", "dateline": null}