{"company_codes_occur": "", "art": "", "company_codes_association": "", "language_code": "en", "person_codes": "", "word_count": 100, "an": "PAPRIN0020191005efa300038", "region_of_origin": "ASIA PAKIS SASIAZ ", "company_codes": "", "publication_date": 1570060800000, "market_index_codes": "", "source_name": "Pakistan Press International", "company_codes_relevance_ticker_exchange": "", "publisher_name": "Pakistan Press International Information Services", "ingestion_datetime": 1570273638000, "document_type": "article", "byline": "", "copyright": "Copyright \u00a9 2019. Pakistan Press International ", "title": "GB: (Function in connection with Chinese National Day held in Gilgit)", "section": "", "company_codes_occur_ticker_exchange": "", "snippet": "A function in connection with Chinese National Day was held in Gilgit. It was organized by Chines overseas foundation, Gilgit-Baltistan. Speaking on the occasion Minister works Dr Muhammad Iqbal congratulated Chinese for their national day celebrations.\n\nHe said Pakistan and China are time tasted friends enjoining cordial relations. Deputy Speaker Gilgit-Baltistan Assembly Jafarullah Khan said CPEC project will further strengthen ties between both friend countries.", "company_codes_relevance": "", "body": "He paid tributes to Chines Leader Mao who put china on path of development and prosperity. Later, they cut birth anniversary cake.", "subject_codes": "", "company_codes_association_ticker_exchange": "", "company_codes_lineage": "", "source_code": "PAPRIN", "industry_codes": "", "modification_datetime": 1570273638000, "currency_codes": "", "modification_date": 1585480430818, "region_codes": ",pakis,china,apacz,asiaz,bric,chinaz,devgcoz,dvpcoz,easiaz,indsubz,sasiaz,", "company_codes_lineage_ticker_exchange": "", "company_codes_ticker_exchange": "", "credit": "", "publication_datetime": 1570060800000, "company_codes_about_ticker_exchange": "", "company_codes_about": "", "action": "add", "dateline": null}