{"company_codes_occur": "", "art": "", "company_codes_association": "", "language_code": "en", "person_codes": "", "word_count": 178, "an": "ASDAWN0020191005efa50001h", "region_of_origin": "ASIA PAKIS SASIAZ ", "company_codes": "", "publication_date": 1570233600000, "market_index_codes": "", "source_name": "Dawn", "company_codes_relevance_ticker_exchange": "", "publisher_name": "Pakistan Herald Publications (Pvt.) Limited", "ingestion_datetime": 1570255084000, "document_type": "article", "byline": "", "copyright": "Copyright \u00a9 2019. Dawn ", "title": "China gifts goods worth $200,000 to Gwadar fishermen", "section": "", "company_codes_occur_ticker_exchange": "", "snippet": "In view of the problems being faced by the fishermen of Gwadar, China has gifted to them fishing equipment and machinery worth $200,000.\n\nEngines of fishing boats, small solar systems and latest fishing nets were included in the goods that were handed over by Chinese Consul General in Karachi Wang Yu to the chairman of the Gwadar Fishermen Alliance, Khudadad Wajo, on Wednesday.", "company_codes_relevance": "", "body": "'The Chinese government will provide more aid to Balochistan, including Gwadar, under the socio-economic development phase of the China-Pakistan Economic Corridor (CPEC), which will address the issues that common people are facing,' Mr Wang said on the occasion.\n\nHe said the strategic ties between Pakistan and China have been on an upward trajectory since the launch of CPEC, which would also address the economic backwardness of Balochistan. The people would get opportunities to enjoy the fruits of economic development, he said and added that natural resources and promising sectors would be explored and efforts made to promote the strategic location of the province.", "subject_codes": ",gangl,gspo,ncat,nfact,nfce,nrgn,", "company_codes_association_ticker_exchange": "", "company_codes_lineage": "", "source_code": "ASDAWN", "industry_codes": "", "modification_datetime": 1570255084000, "currency_codes": "", "modification_date": 1585483574669, "region_codes": ",pakis,china,karch,apacz,asiaz,bric,chinaz,devgcoz,dvpcoz,easiaz,indsubz,sasiaz,", "company_codes_lineage_ticker_exchange": "", "company_codes_ticker_exchange": "", "credit": "", "publication_datetime": 1570233600000, "company_codes_about_ticker_exchange": "", "company_codes_about": "", "action": "add", "dateline": null}