{"company_codes_occur": "", "art": "", "company_codes_association": "", "language_code": "en", "person_codes": "", "word_count": 184, "an": "NBFSTA0020190114ef1e00085", "region_of_origin": "ASIA PAKIS SASIAZ ", "company_codes": "", "publication_date": 1547424000000, "market_index_codes": "", "source_name": "Frontier Star", "company_codes_relevance_ticker_exchange": "", "publisher_name": "Frontier Star Publisher", "ingestion_datetime": 1547447367000, "document_type": "article", "byline": "", "copyright": "\u00a9 2019 Asianet-Pakistan ", "title": "Land acquisition for Allama Iqbal Industrial City to start this year", "section": "", "company_codes_occur_ticker_exchange": "", "snippet": "The state-of-the-art Allama Iqbal Industrial City is being established to accelerate industrial activities and land acquisition process for this project would be started in current financial year.\n\nThis was stated by the spokesman of Faisalabad Industrial Estate Development and Management Company (FIEDMC) while talking to reporter here on Sunday. He said that the government had already sanctioned Rs 6. 3 billion for this mega project which will spur industrial activities in this industrial city.", "company_codes_relevance": "", "body": "He said that this project is adjacent to the existing Special Economic Zone of M-3 Industrial Estate and located in close proximity with Sahianwala Interchange of Motorway (M-3). This industrial city will house textile, steel, pharmaceuticals, engineering, chemicals, food processing, plastics and agricultural appliances units.\n\n'It is sprawling over approximately 3, 000 acres of land and will be a part of China Pakistan Economic Corridor (CPEC)', he said, adding that the government is also expecting that Chinese will establish new units in this city as well as relocation of their industrial units from China.", "subject_codes": "", "company_codes_association_ticker_exchange": "", "company_codes_lineage": "", "source_code": "NBFSTA", "industry_codes": "", "modification_datetime": 1547447367000, "currency_codes": "", "modification_date": 1585483728189, "region_codes": ",pakis,asiaz,devgcoz,dvpcoz,indsubz,sasiaz,", "company_codes_lineage_ticker_exchange": "", "company_codes_ticker_exchange": "", "credit": "", "publication_datetime": 1547424000000, "company_codes_about_ticker_exchange": "", "company_codes_about": "", "action": "add", "dateline": null}